computational_stopwatch/__init__.py
computational_stopwatch/stopwatch.py
computational_stopwatch-1.0.5.dist-info/LICENSE
computational_stopwatch-1.0.5.dist-info/METADATA
computational_stopwatch-1.0.5.dist-info/WHEEL
computational_stopwatch-1.0.5.dist-info/top_level.txt
computational_stopwatch-1.0.5.dist-info/RECORD
