Metadata-Version: 2.1
Name: computational-stopwatch
Version: 1.0.5
Summary: Simple stopwatch to easily print the elapsed time of a set of operations
Home-page: https://gitlab.com/luca.baronti/computational-stopwatch
Download-URL: https://pypi.org/project/computational_stopwatch/
Author: Luca Baronti
Author-email: lbaronti@gmail.com
License: GNUv3
Keywords: computation,time,elapsed time
Platform: UNKNOWN
Classifier: Development Status :: 5 - Production/Stable
Classifier: Intended Audience :: Developers
Classifier: Topic :: Software Development
Classifier: License :: OSI Approved :: GNU General Public License v3 (GPLv3)
Classifier: Programming Language :: Python :: 3
License-File: LICENSE
